LICENSE
MANIFEST.in
README.md
pyproject.toml
setup.cfg
setup.py
src/c/Condat_TV_1D_v2.c
src/condat_tv/__init__.py
src/condat_tv/tv.c
src/condat_tv/tv.pyx
src/condat_tv.egg-info/PKG-INFO
src/condat_tv.egg-info/SOURCES.txt
src/condat_tv.egg-info/dependency_links.txt
src/condat_tv.egg-info/not-zip-safe
src/condat_tv.egg-info/requires.txt
src/condat_tv.egg-info/top_level.txt