Metadata-Version: 2.1
Name: condat-tv
Version: 0.0.5
Summary: Cython wrapper for the efficient TV denoising algorithm by Condat
Home-page: https://github.com/marieroald/condat_tv
Author: Marie Roald & Yngve Mardal Moe
Author-email: yngve.m.moe@gmail.com
License: "GNU General Public License v3",
Platform: UNKNOWN
Classifier: Development Status :: 2 - Pre-Alpha
Classifier: Intended Audience :: Developers
Classifier: License :: OSI Approved :: GNU General Public License v3 (GPLv3)
Classifier: Natural Language :: English
Classifier: Programming Language :: Python :: 3.6
Classifier: Programming Language :: Python :: 3.7
License-File: LICENSE
